IQDM/__init__.py
IQDM/delta4_trending.py
IQDM/main.py
IQDM/pdf_to_text.py
IQDM/pdf_to_text_data.py
IQDM/plot_test.py
IQDM/trending.py
IQDM/trending_arccheck.py
IQDM/trending_delta4.py
IQDM/utilities.py
IQDM/parsers/__init__.py
IQDM/parsers/delta4.py
IQDM/parsers/mapcheck2_parser.py
IQDM/parsers/parser.py
IQDM/parsers/sncpatient.py
IQDM-0.3.1.post1.dist-info/LICENSE
IQDM-0.3.1.post1.dist-info/METADATA
IQDM-0.3.1.post1.dist-info/WHEEL
IQDM-0.3.1.post1.dist-info/entry_points.txt
IQDM-0.3.1.post1.dist-info/top_level.txt
IQDM-0.3.1.post1.dist-info/RECORD
